jimg_cli/__init__.py
jimg_cli/image.py
jimg_cli-0.1.4.dist-info/METADATA
jimg_cli-0.1.4.dist-info/WHEEL
jimg_cli-0.1.4.dist-info/entry_points.txt
jimg_cli-0.1.4.dist-info/RECORD
