Metadata-Version: 2.4
Name: jimg_cli
Version: 0.1.4
Summary: image processing cli
Requires-Python: >=3.12
Requires-Dist: imageio>=2.36.1
Requires-Dist: opencv-python>=4.10.0.84
Requires-Dist: pillow>=11.0.0
Requires-Dist: typer>=0.15.1
